vision_oslo_extension/__init__.py
vision_oslo_extension/additional_frame.py
vision_oslo_extension/average_load.py
vision_oslo_extension/base_frame.py
vision_oslo_extension/batch_processing.py
vision_oslo_extension/battery_processing.py
vision_oslo_extension/battery_processing_new.py
vision_oslo_extension/bhtpbank_check.py
vision_oslo_extension/check_frame.py
vision_oslo_extension/cif_output_analysis.py
vision_oslo_extension/cif_prepare.py
vision_oslo_extension/data/ABB_Potteric_Carr.csv
vision_oslo_extension/data/Siemens_Hambleton_Jcn.csv
vision_oslo_extension/data/tiploc_library(DO_NOT_USE).csv
vision_oslo_extension/dc_falling_voltage_protection.py
vision_oslo_extension/dc_single_end_feeding.py
vision_oslo_extension/dc_summary.py
vision_oslo_extension/extraction_frame.py
vision_oslo_extension/fs_bemu_capacity.py
vision_oslo_extension/grid_connection.py
vision_oslo_extension/gui_start.py
vision_oslo_extension/input_frame.py
vision_oslo_extension/licensing.py
vision_oslo_extension/list_file_processing.py
vision_oslo_extension/low_v_summary.py
vision_oslo_extension/main_page_frame.py
vision_oslo_extension/master.py
vision_oslo_extension/model_check.py
vision_oslo_extension/ole_processing.py
vision_oslo_extension/oslo_extraction.py
vision_oslo_extension/processing_frame.py
vision_oslo_extension/protection_if.py
vision_oslo_extension/rn26/osop.exe
vision_oslo_extension/rn27/osop.exe
vision_oslo_extension/rn29/osop.exe
vision_oslo_extension/sfc_assess.py
vision_oslo_extension/shared_contents.py
vision_oslo_extension/shared_excel_helper.py
vision_oslo_extension/simulation_batch_run.py
vision_oslo_extension/support/ac_extra_oslo_creator.xlsm
vision_oslo_extension/support/ac_oslo_section_impedance.xlsx
vision_oslo_extension/support/BatchControlTemplate.csv
vision_oslo_extension/support/battery_bhtpbank_file_creator.xlsm
vision_oslo_extension/support/battery_train_template.xlsx
vision_oslo_extension/support/battery_train_template_new.xlsx
vision_oslo_extension-3.13.1.dist-info/LICENSE
vision_oslo_extension-3.13.1.dist-info/METADATA
vision_oslo_extension-3.13.1.dist-info/WHEEL
vision_oslo_extension-3.13.1.dist-info/RECORD
