Metadata-Version: 2.3
Name: vision_oslo_extension
Version: 3.13.1
Summary: This is the package to support additional features on VISION-OSLO, software owned by Network Rail Infrastructure Limited.
License: Open Source Non-Commercial License (OSNCL) v1.0
Author: Jieming Ye
Author-email: Jieming.Ye@networkrail.co.uk
Requires-Python: >=3.10
Classifier: License :: Other/Proprietary License
Classifier: Operating System :: OS Independent
Classifier: Programming Language :: Python :: 3
Classifier: Programming Language :: Python :: 3.10
Classifier: Programming Language :: Python :: 3.11
Classifier: Programming Language :: Python :: 3.12
Classifier: Programming Language :: Python :: 3.13
Requires-Dist: matplotlib
Requires-Dist: networkx
Requires-Dist: numpy
Requires-Dist: openpyxl (==3.1.2)
Requires-Dist: pandas (==2.3.3)
Requires-Dist: psutil
Requires-Dist: pywinauto
Requires-Dist: requests
Requires-Dist: scipy
Requires-Dist: tk
Requires-Dist: xlsxwriter
Project-URL: Homepage, https://pypi.org/project/vision-oslo-extension/
